{"GlobalPropertiesHash":"2ilJ2M8+ZdH0swl4cXFj9Ji8kay0R08ISE/fEc+OL0o=","FingerprintPatternsHash":"8ZRc1sGeVrPBx4lD717BgRaQekyh78QKV9SKsdt638U=","PropertyOverridesHash":"8ZRc1sGeVrPBx4lD717BgRaQekyh78QKV9SKsdt638U=","InputHashes":["ME0Cw8gKv/AtOrHn23FRmrfr9Xcz1ZgR2uneJJcnjhQ=","zwLKz1vPyoo6Uavbc0T/Oi6aAoP\u002Bfk8P4VSAJzSBXiI="],"CachedAssets":{"ME0Cw8gKv/AtOrHn23FRmrfr9Xcz1ZgR2uneJJcnjhQ=":{"Identity":"C:\\Users\\grego\\Downloads\\GoldClub\\GoldClub\\obj\\Debug\\net10.0\\compressed\\4t4de3fu5g-{0}-gifyjkn2z2-gifyjkn2z2.gz","SourceId":"GoldClub","SourceType":"Discovered","ContentRoot":"C:\\Users\\grego\\Downloads\\GoldClub\\GoldClub\\obj\\Debug\\net10.0\\compressed\\","BasePath":"/","RelativePath":"css/site#[.{fingerprint=gifyjkn2z2}]?.css.gz","AssetKind":"All","AssetMode":"All","AssetRole":"Alternative","AssetMergeBehavior":null,"AssetMergeSource":"","RelatedAsset":"C:\\Users\\grego\\Downloads\\GoldClub\\GoldClub\\wwwroot\\css\\site.css","AssetTraitName":"Content-Encoding","AssetTraitValue":"gzip","Fingerprint":"5hff480ad7","Integrity":"59/xNZ9v4AiHPBRQi0MGDJULRHj/GKNgmZElB6lfhBg=","CopyToOutputDirectory":"Never","CopyToPublishDirectory":"PreserveNewest","OriginalItemSpec":"C:\\Users\\grego\\Downloads\\GoldClub\\GoldClub\\wwwroot\\css\\site.css","FileLength":2727,"LastWriteTime":"2026-06-18T23:20:02.8135726+00:00"},"zwLKz1vPyoo6Uavbc0T/Oi6aAoP\u002Bfk8P4VSAJzSBXiI=":{"Identity":"C:\\Users\\grego\\Downloads\\GoldClub\\GoldClub\\obj\\Debug\\net10.0\\compressed\\gfv836xsin-{0}-eo85mfb3sw-eo85mfb3sw.gz","SourceId":"GoldClub","SourceType":"Discovered","ContentRoot":"C:\\Users\\grego\\Downloads\\GoldClub\\GoldClub\\obj\\Debug\\net10.0\\compressed\\","BasePath":"/","RelativePath":"js/site#[.{fingerprint=eo85mfb3sw}]?.js.gz","AssetKind":"All","AssetMode":"All","AssetRole":"Alternative","AssetMergeBehavior":null,"AssetMergeSource":"","RelatedAsset":"C:\\Users\\grego\\Downloads\\GoldClub\\GoldClub\\wwwroot\\js\\site.js","AssetTraitName":"Content-Encoding","AssetTraitValue":"gzip","Fingerprint":"a2125m4qs9","Integrity":"4m5aGFOni51GZNBNZ6v2E/KEYzoPGCsjR7wQDL6Z3go=","CopyToOutputDirectory":"Never","CopyToPublishDirectory":"PreserveNewest","OriginalItemSpec":"C:\\Users\\grego\\Downloads\\GoldClub\\GoldClub\\wwwroot\\js\\site.js","FileLength":397,"LastWriteTime":"2026-06-18T23:20:02.8135726+00:00"}},"CachedCopyCandidates":{}}